MANIFEST.in
README.md
setup.cfg
setup.py
django_GNU_Terry_Pratchett.egg-info/PKG-INFO
django_GNU_Terry_Pratchett.egg-info/SOURCES.txt
django_GNU_Terry_Pratchett.egg-info/dependency_links.txt
django_GNU_Terry_Pratchett.egg-info/not-zip-safe
django_GNU_Terry_Pratchett.egg-info/top_level.txt
gnu_terry_pratchett/__init__.py
gnu_terry_pratchett/decorators.py
gnu_terry_pratchett/middleware.py
gnu_terry_pratchett/models.py
gnu_terry_pratchett/views.py