Metadata-Version: 1.1
Name: django-GNU-Terry-Pratchett
Version: 0.2.0
Summary: You know they'll never really die while the Trunk is alive
Home-page: https://github.com/aaronbassett/django-GNU-Terry-Pratchett
Author: Aaron Bassett
Author-email: aaron@rawtech.io
License: BSD
Platform: UNKNOWN
Classifier: Framework :: Django
Classifier: Intended Audience :: Developers
Classifier: License :: OSI Approved :: BSD License
Classifier: Natural Language :: English
Classifier: Programming Language :: Python :: 2
Classifier: Programming Language :: Python :: 2.6
Classifier: Programming Language :: Python :: 2.7
Classifier: Programming Language :: Python :: 3
Classifier: Programming Language :: Python :: 3.3
